LICENSE
MANIFEST.in
README.rst
setup.py
Clinamen.egg-info/PKG-INFO
Clinamen.egg-info/SOURCES.txt
Clinamen.egg-info/dependency_links.txt
Clinamen.egg-info/requires.txt
Clinamen.egg-info/top_level.txt
clinamen/__about__.py
clinamen/__init__.py
clinamen/utils.py
clinamen/cmaes/__init__.py
clinamen/cmaes/evolution.py
clinamen/cmaes/fitness_calculators.py
clinamen/cmaes/population_evolver.py
clinamen/descriptors/__init__.py
clinamen/descriptors/basic_operations.c
clinamen/descriptors/basic_operations.h
clinamen/descriptors/descriptors.py
clinamen/descriptors/finger_descriptors_c.c
clinamen/descriptors/finger_descriptors_c.h
clinamen/descriptors/finger_descriptors_cython.c
clinamen/descriptors/finger_descriptors_cython.pyx
clinamen/descriptors/setup.py
clinamen/descriptors/utils.py
clinamen/evpd/__init__.py
clinamen/evpd/core/__init__.py
clinamen/evpd/core/individual.py
clinamen/evpd/core/population.py
clinamen/metamodel/__init__.py
clinamen/metamodel/gp_models.py
clinamen/metamodel/metamodel.py
clinamen/metamodel/utils.py