Metadata-Version: 2.1
Name: Clinamen
Version: 0.2.0a3
Summary: Clinamen: a Python package for the first-principles systematic discovery of low-energy configurations in defective systems.
Home-page: https://gitlab.com/Marrigoni/clinamen
Author: Marco Arrigoni
Author-email: marco.arrigoni@outlook.de
License: Apache License 2.0
Platform: UNKNOWN
Classifier: Development Status :: 3 - Alpha
Classifier: Operating System :: OS Independent
Classifier: Intended Audience :: Science/Research
Classifier: License :: OSI Approved :: Apache Software License
Classifier: Topic :: Scientific/Engineering :: Chemistry
Classifier: Topic :: Scientific/Engineering :: Physics
Classifier: Programming Language :: Python :: 3
Classifier: Programming Language :: C
Classifier: Programming Language :: Cython
Requires-Python: >=3.8
